data_structures/__init__.py
data_structures/avl_tree.py
data_structures/binary_search_tree.py
data_structures/doubly_linked_list.py
data_structures/linked_list.py
data_structures/node.py
data_structures/queues.py
data_structures/red_black_tree.py
data_structures/stack.py
pyds_fundamental-0.1.5.dist-info/licenses/LICENSE
pyds_fundamental-0.1.5.dist-info/METADATA
pyds_fundamental-0.1.5.dist-info/WHEEL
pyds_fundamental-0.1.5.dist-info/top_level.txt
pyds_fundamental-0.1.5.dist-info/RECORD
