Metadata-Version: 2.4
Name: pyds-fundamental
Version: 0.1.5
Summary: Production-ready implementation of fundamental data structures implemented in Python
Author-email: Emre Kahraman CANIKOGLU <ankaraunifedaisi@gmail.com>
License: MIT
Project-URL: Homepage, https://github.com/999-juicewrld/data_structures
Project-URL: Documentation, https://999-juicewrld.github.io/data_structures/data_structures.html
Project-URL: Repository, https://github.com/999-juicewrld/data_structures
Requires-Python: >=3.10
License-File: LICENSE
Dynamic: license-file
